[
  {
    "title": "Data Union",
    "description": "Data Collaboration for Data-Centric AI.",
    "creator": ["robinlehman"],
    "url": "https://www.dataunion.app/",
    "image": "data_union.jpg",
    "category": ["project"]
  },
  {
    "title": "Algovera.ai",
    "description": "AI workflows for every need.",
    "creator": ["richardblythman"],
    "url": "https://app.algovera.ai/",
    "image": "algovera.jpg",
    "category": ["project"]
  },
  {
    "title": "Autobots",
    "description": "Data Farming intelligence.",
    "creator": ["autobot"],
    "url": "https://autobotocean.com/",
    "image": "autobot.jpg",
    "category": ["project"]
  }
]
